Functvs/__init__.py
functvs-0.0.1.dist-info/METADATA
functvs-0.0.1.dist-info/WHEEL
functvs-0.0.1.dist-info/licenses/LICENSE
functvs-0.0.1.dist-info/RECORD
